viphoneme/Popular.txt
viphoneme/T2IPA.py
viphoneme/__init__.py
viphoneme/get_english_sym.py
viphoneme/restore.txt
viphoneme/syms.py
viphoneme/test.py
viphoneme/text2sequence.py
viphoneme-3.0.0.dist-info/LICENSE
viphoneme-3.0.0.dist-info/METADATA
viphoneme-3.0.0.dist-info/WHEEL
viphoneme-3.0.0.dist-info/top_level.txt
viphoneme-3.0.0.dist-info/RECORD
