Metadata-Version: 2.1
Name: viphoneme
Version: 3.0.0
Summary: Python package for convert text to phoneme ipa, use for cross language embedding Text-to-speech Reseach
Home-page: https://github.com/v-nhandt21/Viphoneme
Author: AILAB
Author-email: dotrinhan99@gmail.com
License: AILAB
Platform: UNKNOWN
Classifier: Development Status :: 4 - Beta
Classifier: License :: Free for non-commercial use
Classifier: Natural Language :: Vietnamese
Classifier: Operating System :: POSIX :: Linux
Classifier: Programming Language :: C++
Classifier: Programming Language :: Python :: 3.6
Classifier: Topic :: Scientific/Engineering :: Artificial Intelligence
